setup.py
timeprint.py
timeprint.egg-info/PKG-INFO
timeprint.egg-info/SOURCES.txt
timeprint.egg-info/dependency_links.txt
timeprint.egg-info/top_level.txt