Metadata-Version: 1.0
Name: timeprint
Version: 0.0.1
Summary: Context manager and decorator for showing time elapsed.
Home-page: https://github.com/raymondbutcher/python-timeprint
Author: Raymond Butcher
Author-email: randomy@gmail.com
License: MIT
Platform: UNKNOWN
